remappy/__init__.py
remappy/plot_it.py
remappy/remap.py
remappy-0.0.0.8.data/scripts/remap.py
remappy-0.0.0.8.dist-info/LICENSE
remappy-0.0.0.8.dist-info/METADATA
remappy-0.0.0.8.dist-info/WHEEL
remappy-0.0.0.8.dist-info/top_level.txt
remappy-0.0.0.8.dist-info/RECORD
