Metadata-Version: 2.1
Name: remappy
Version: 0.0.0.8
Summary: Reaction-Transport Modeling in Porous Media
Home-page: https://github.com/uliw/remappy
Author: Ulrich G. Wortmann
Author-email: uli.wortmann@utoronto.ca
License: GPL-3.0-or-later
Platform: UNKNOWN
Classifier: Programming Language :: Python :: 3
Classifier: License :: OSI Approved :: GNU Lesser General Public License v3 (LGPLv3)
Classifier: Operating System :: OS Independent
Classifier: Intended Audience :: Education
Classifier: Intended Audience :: Science/Research
Classifier: Topic :: Scientific/Engineering :: Chemistry
Classifier: License :: OSI Approved :: GNU Lesser General Public License v3 or later (LGPLv3+)
License-File: LICENSE
